coronapy/__init__.py
coronapy/cli.py
coronapy/lib/__init__.py
coronapy/lib/color.py
coronapy/lib/get_countries.py
coronapy/lib/get_country.py
coronapy/lib/get_world_wide.py
coronapy_cli-1.3.2.dist-info/LICENSE.txt
coronapy_cli-1.3.2.dist-info/METADATA
coronapy_cli-1.3.2.dist-info/WHEEL
coronapy_cli-1.3.2.dist-info/entry_points.txt
coronapy_cli-1.3.2.dist-info/top_level.txt
coronapy_cli-1.3.2.dist-info/RECORD
