Metadata-Version: 2.1
Name: coronapy-cli
Version: 1.3.2
Summary: A command line tool to fetch worldwide data about Corona Virus
Home-page: https://github.com/MouadBH/coronapy-cli
Author: MouadBH
Author-email: mouad123b@gmail.com
License: MIT
Keywords: corona,covid-19,cli,corona-cli,coronavirus, coronavirus-tracking,coronavirus-real-time, coronavirus-info
Platform: UNKNOWN
Classifier: Programming Language :: Python :: 3
Classifier: Programming Language :: Python :: 3.7
Classifier: License :: OSI Approved :: MIT License
Classifier: Operating System :: OS Independent
Requires-Python: >=3.6
Requires-Dist: Click
Requires-Dist: pyfiglet
Requires-Dist: prettytable
Requires-Dist: yaspin
Requires-Dist: termgraph
Requires-Dist: colorama
Requires-Dist: termcolor
